matrix_rotation/__init__.py
matrix_rotation/image_rotation.py
matrix_rotation/matrix_rotation.py
matrix_rotation/matrix_rotation_cli.py
matrix_rotation-0.2.2.dist-info/LICENSE
matrix_rotation-0.2.2.dist-info/METADATA
matrix_rotation-0.2.2.dist-info/WHEEL
matrix_rotation-0.2.2.dist-info/entry_points.txt
matrix_rotation-0.2.2.dist-info/top_level.txt
matrix_rotation-0.2.2.dist-info/RECORD
