Metadata-Version: 2.1
Name: matrix-rotation
Version: 0.2.2
Summary: Rotate any square matrix clockwise and anticlockwise in any degree of angle.
Home-page: https://github.com/vhiwase/matrix-rotation
Author: Vaibhav Hiwase
Author-email: hiwase.vaibhav@gmail.com
License: MIT license
Keywords: matrix_rotation
Platform: UNKNOWN
Classifier: Development Status :: 4 - Beta
Classifier: Intended Audience :: Developers
Classifier: License :: OSI Approved :: MIT License
Classifier: Natural Language :: English
Classifier: Programming Language :: Python :: 3
Classifier: Programming Language :: Python :: 3.6
Classifier: Programming Language :: Python :: 3.7
Classifier: Programming Language :: Python :: 3.8
Classifier: Programming Language :: Python :: 3.9
Requires-Python: >=3.6
Requires-Dist: click (>=7.1.2)
Requires-Dist: numpy (>=1.18.5)
Requires-Dist: opencv-python
Requires-Dist: pathlib (>=1.0.1)
